pybiginteger-stubs/__init__.pyi
pybiginteger_stubs-1.3.5.dist-info/METADATA
pybiginteger_stubs-1.3.5.dist-info/WHEEL
pybiginteger_stubs-1.3.5.dist-info/top_level.txt
pybiginteger_stubs-1.3.5.dist-info/RECORD
