Metadata-Version: 2.4
Name: pybiginteger-stubs
Version: 1.3.5
Summary: PEP 561 type stubs for pybiginteger
Maintainer: Erik van den Brink
Maintainer-email: erik@coz.io
Requires-Dist: pybiginteger==1.3.5
Dynamic: maintainer
Dynamic: maintainer-email
Dynamic: requires-dist
Dynamic: summary
